{
  "heroes": [
    {
      "id": 11,
      "name": "Dr Nice",
      "powerStats": {
        "combat": 19,
        "speed": 9,
        "intelligence": 10,
        "strength": 4,
        "overallRating": 42
      }
    },
    {
      "id": 12,
      "name": "Narco",
      "powerStats": {
        "combat": 9,
        "speed": 4990,
        "intelligence": 5,
        "strength": 5,
        "overallRating": 5009
      }
    },
    {
      "id": 13,
      "name": "Bombasto",
      "powerStats": {
        "combat": 8,
        "speed": 900,
        "intelligence": 80,
        "strength": 10,
        "overallRating": 998
      }
    },
    {
      "id": 14,
      "name": "Celeritas",
      "powerStats": {
        "combat": 6,
        "speed": 18,
        "intelligence": 90,
        "strength": 8,
        "overallRating": 122
      }
    },
    {
      "id": 15,
      "name": "Magneta",
      "powerStats": {
        "combat": 100,
        "speed": 10,
        "intelligence": 2,
        "strength": 8,
        "overallRating": 120
      }
    },
    {
      "id": 16,
      "name": "RubberMan",
      "powerStats": {
        "combat": 1,
        "speed": 5,
        "intelligence": 8,
        "strength": 10,
        "overallRating": 24
      }
    },
    {
      "id": 17,
      "name": "Dynama",
      "powerStats": {
        "combat": 5,
        "speed": 7,
        "intelligence": 8,
        "strength": 9,
        "overallRating": 29
      }
    },
    {
      "id": 18,
      "name": "Dr IQ",
      "powerStats": {
        "combat": 89,
        "speed": 18,
        "intelligence": 28,
        "strength": 56,
        "overallRating": 191
      }
    },
    {
      "id": 19,
      "name": "Magma",
      "powerStats": {
        "combat": 80,
        "speed": 22,
        "intelligence": 8,
        "strength": 11,
        "overallRating": 121
      }
    },
    {
      "id": 20,
      "name": "Tornado",
      "powerStats": {
        "combat": 8,
        "speed": 90,
        "intelligence": 90,
        "strength": 50,
        "overallRating": 238
      }
    }
  ]
}